ULLRPALIB/Convert_XLS_to_XLSX.py
ULLRPALIB/DatosUXXIEC.py
ULLRPALIB/Drive.py
ULLRPALIB/Excel.py
ULLRPALIB/General.py
ULLRPALIB/Telegram.py
ULLRPALIB/Test_SRC_ULLRPALIB.py
ULLRPALIB/Test_ULLRPALIB.py
ULLRPALIB/__init__.py
ULLRPALIB-2024.1.3.dist-info/METADATA
ULLRPALIB-2024.1.3.dist-info/WHEEL
ULLRPALIB-2024.1.3.dist-info/top_level.txt
ULLRPALIB-2024.1.3.dist-info/RECORD
