Metadata-Version: 2.1
Name: ULLRPALIB
Version: 2024.1.3
Summary: Librería para utilidades generales de RPA para Python
Home-page: https://github.com/RPA-ULL/0998_LIB_Python_Scripts
Author: ULL-RPA
Author-email: gerencia.sce.ticger@ull.edu.es
License: MIT
Requires-Dist: openpyxl
Requires-Dist: pandas
Requires-Dist: xlrd
Requires-Dist: pywin32
Requires-Dist: python-telegram-bot
Requires-Dist: asyncio
Requires-Dist: driveup
